motivationalqpy/__init__.py
motivationalqpy/quotes.py
motivationalqpy-0.1.dist-info/METADATA
motivationalqpy-0.1.dist-info/WHEEL
motivationalqpy-0.1.dist-info/top_level.txt
motivationalqpy-0.1.dist-info/RECORD
