Metadata-Version: 2.1
Name: motivationalqpy
Version: 0.1
Summary: A minimal package for motivational quotes
Author: darkbit
Author-email: darkbit131@gmail.com
Keywords: motivation,quotes,inspiration
Classifier: Development Status :: 3 - Alpha
Classifier: Intended Audience :: Developers
Classifier: Topic :: Software Development :: Build Tools
Classifier: License :: OSI Approved :: MIT License
Classifier: Programming Language :: Python :: 3
Classifier: Programming Language :: Python :: 3.7
Classifier: Programming Language :: Python :: 3.8
Classifier: Programming Language :: Python :: 3.9
Classifier: Programming Language :: Python :: 3.10
Classifier: Programming Language :: Python :: 3.11
